ldlite/__init__.py
ldlite/_camelcase.py
ldlite/_csv.py
ldlite/_jsonx.py
ldlite/_query.py
ldlite/_request.py
ldlite/_select.py
ldlite/_sqlx.py
ldlite/_xlsx.py
ldlite/py.typed
suub_ldlite-3.0.0.dist-info/METADATA
suub_ldlite-3.0.0.dist-info/WHEEL
suub_ldlite-3.0.0.dist-info/entry_points.txt
suub_ldlite-3.0.0.dist-info/licenses/LICENSE
suub_ldlite-3.0.0.dist-info/RECORD
