Metadata-Version: 2.1
Name: suub-ldlite
Version: 3.0.0
Summary: Lightweight analytics tool for FOLIO services
Author-Email: Katherine Bargar <kbargar@fivecolleges.edu>, Nassib Nassar <nassib@indexdata.com>
License: Apache-2.0
Classifier: License :: OSI Approved :: Apache Software License
Classifier: Operating System :: OS Independent
Classifier: Programming Language :: Python :: 3
Project-URL: Homepage, https://github.com/library-data-platform/ldlite
Project-URL: Bug Tracker, https://github.com/library-data-platform/ldlite/issues
Requires-Python: >=3.9
Requires-Dist: duckdb>=0.6.1
Requires-Dist: psycopg2>=2.9.5
Requires-Dist: requests>=2.28.2
Requires-Dist: tqdm>=4.64.1
Requires-Dist: XlsxWriter>=3.0.6
